LICENSE
MANIFEST.in
README.md
setup.py
scripts/stream_tweets
tests/__init__.py
tests/test_checker.py
tests/test_listener.py
tests/test_stream.py
tests/basic_stream/__init__.py
tests/basic_stream/test_basic_file_term_checker.py
tests/basic_stream/test_basic_stream.py
tests/basic_stream/test_printing_listener.py
twitter_monitor/__init__.py
twitter_monitor/basic_stream.py
twitter_monitor/checker.py
twitter_monitor/listener.py
twitter_monitor/stream.py
twitter_monitor.egg-info/PKG-INFO
twitter_monitor.egg-info/SOURCES.txt
twitter_monitor.egg-info/dependency_links.txt
twitter_monitor.egg-info/requires.txt
twitter_monitor.egg-info/top_level.txt