Metadata-Version: 1.1
Name: twitter-monitor
Version: 0.2.9
Summary: A Twitter streaming library built on tweepy that enables dynamic term tracking
Home-page: https://github.com/michaelbrooks/twitter-monitor
Author: Michael Brooks
Author-email: mjbrooks@uw.edu
License: MIT
Download-URL: https://github.com/michaelbrooks/twitter-monitor/archive/v0.2.9.zip
Keywords: twitter,streaming,tweepy,filter
Platform: UNKNOWN
Classifier: Development Status :: 3 - Alpha
Classifier: Topic :: Utilities
Classifier: License :: OSI Approved :: MIT License
